getotp/__init__.py
getotp/version.py
getotp-0.1.0.data/scripts/getotp
getotp-0.1.0.dist-info/LICENSE
getotp-0.1.0.dist-info/METADATA
getotp-0.1.0.dist-info/WHEEL
getotp-0.1.0.dist-info/top_level.txt
getotp-0.1.0.dist-info/RECORD
